discordpingformatter/__init__.py
discordpingformatter/admin.py
discordpingformatter/app_settings.py
discordpingformatter/apps.py
discordpingformatter/auth_hooks.py
discordpingformatter/models.py
discordpingformatter/tasks.py
discordpingformatter/tests.py
discordpingformatter/urls.py
discordpingformatter/utils.py
discordpingformatter/views.py
discordpingformatter/docs/aa-view.jpg
discordpingformatter/docs/discord-ping.jpg
discordpingformatter/docs/ping-examples.jpg
discordpingformatter/migrations/0001_initial.py
discordpingformatter/migrations/__init__.py
discordpingformatter/static/discordpingformatter/js/discordpingformatter.dev.js
discordpingformatter/static/discordpingformatter/js/discordpingformatter.js
discordpingformatter/static/discordpingformatter/js/discordpingformatter.min.js
discordpingformatter/static/discordpingformatter/js/copy-to-clipboard/copy-to-clipboard.min.js
discordpingformatter/templates/discordpingformatter/base.html
discordpingformatter/templates/discordpingformatter/form.html
discordpingformatter/templates/discordpingformatter/index.html
discordpingformatter/templates/discordpingformatter/ping.html
discordpingformatter/templates/discordpingformatter/form/additionalInformation.html
discordpingformatter/templates/discordpingformatter/form/fleetCommander.html
discordpingformatter/templates/discordpingformatter/form/fleetComms.html
discordpingformatter/templates/discordpingformatter/form/fleetDoctrine.html
discordpingformatter/templates/discordpingformatter/form/fleetName.html
discordpingformatter/templates/discordpingformatter/form/fleetType.html
discordpingformatter/templates/discordpingformatter/form/formupLocation.html
discordpingformatter/templates/discordpingformatter/form/formupTime.html
discordpingformatter/templates/discordpingformatter/form/pingChannel.html
discordpingformatter/templates/discordpingformatter/form/pingTargets.html
discordpingformatter/templates/discordpingformatter/form/prePing.html
aa_discord_ping_formatter-1.1.4.dist-info/LICENSE
aa_discord_ping_formatter-1.1.4.dist-info/METADATA
aa_discord_ping_formatter-1.1.4.dist-info/WHEEL
aa_discord_ping_formatter-1.1.4.dist-info/top_level.txt
aa_discord_ping_formatter-1.1.4.dist-info/RECORD
