Metadata-Version: 2.1
Name: aa-discord-ping-formatter
Version: 1.1.4
Summary: Discord Ping Formatter for Alliance Auth
Home-page: https://github.com/ppfeufer/aa-discord-ping-formatter
Author: Peter Pfeufer
Author-email: development@ppfeufer.de
License: GNU General Public License v3 (GPLv3)
Platform: UNKNOWN
Classifier: Environment :: Web Environment
Classifier: Framework :: Django
Classifier: Framework :: Django :: 2.2
Classifier: Intended Audience :: Developers
Classifier: License :: OSI Approved :: GNU General Public License v3 (GPLv3)
Classifier: Operating System :: OS Independent
Classifier: Programming Language :: Python
Classifier: Programming Language :: Python :: 3.6
Classifier: Programming Language :: Python :: 3.7
Classifier: Programming Language :: Python :: 3.8
Classifier: Topic :: Internet :: WWW/HTTP
Classifier: Topic :: Internet :: WWW/HTTP :: Dynamic Content
Requires-Python: ~=3.6
Requires-Dist: allianceauth (>=2.7.2)
